koach/__init__.py
koach/__main__.py
koach/query.py
koach-1.1.0.dist-info/DESCRIPTION.rst
koach-1.1.0.dist-info/METADATA
koach-1.1.0.dist-info/RECORD
koach-1.1.0.dist-info/WHEEL
koach-1.1.0.dist-info/entry_points.txt
koach-1.1.0.dist-info/metadata.json
koach-1.1.0.dist-info/top_level.txt
