Metadata-Version: 2.0
Name: koach
Version: 1.1.0
Summary: korean spell checker
Home-page: https://github.com/kexplo/koach
Author: Chanwoong Kim
Author-email: me@chanwoong.kim
License: UNKNOWN
Platform: UNKNOWN
Classifier: Development Status :: 4 - Beta
Classifier: Environment :: Console
Classifier: License :: OSI Approved :: MIT License
Classifier: Natural Language :: Korean
Classifier: Programming Language :: Python :: 2
Classifier: Programming Language :: Python :: 2.7
Classifier: Topic :: Utilities
Requires-Dist: beautifulsoup4 (==4.5.1)
Requires-Dist: requests (==2.11.1)
Requires-Dist: click (==6.6)
Requires-Dist: pytest-runner (==2.9)
